HLAGuessr/__init__.py
HLAGuessr/evaluate_data.py
HLAGuessr/infer_hla.py
HLAGuessr/load_model.py
HLAGuessr/model_tools.py
HLAGuessr/processing.py
HLAGuessr/test_model.py
HLAGuessr/Example_validation_data/HLA_grouped_patients.tsv
HLAGuessr/Example_validation_data/alpha_all_files.tsv.gz
HLAGuessr/Example_validation_data/alpha_example.tsv
HLAGuessr/Example_validation_data/beta_all_files.tsv.gz
HLAGuessr/Example_validation_data/beta_example.tsv
HLAGuessr/Training_data/HLA_frequency_for_validation.tsv
HLAGuessr/Training_data/HLA_grouped_patients.tsv
HLAGuessr/Training_data/alpha_cdr3aa_shared_at_least_3.txt
HLAGuessr/Training_data/beta_cdr3aa_shared_at_least_3.txt
HLAGuessr/Training_data/classifier_params_alpha+beta.tsv
HLAGuessr/Training_data/classifier_params_alpha.tsv
HLAGuessr/Training_data/classifier_params_beta.tsv
HLAGuessr/Training_data/inference_all_data_TCRs_sign_HLA.tsv
hlaguessr-0.1.13.data/data/LICENSE
hlaguessr-0.1.13.data/data/MANIFEST.in
hlaguessr-0.1.13.data/data/README.md
hlaguessr-0.1.13.dist-info/LICENSE
hlaguessr-0.1.13.dist-info/METADATA
hlaguessr-0.1.13.dist-info/WHEEL
hlaguessr-0.1.13.dist-info/entry_points.txt
hlaguessr-0.1.13.dist-info/top_level.txt
hlaguessr-0.1.13.dist-info/RECORD
