Metadata-Version: 2.1
Name: hlaguessr
Version: 0.1.13
Summary: HLA typing from alpha and beta T cell repertoires.
Home-page: https://github.com/statbiophys/HLAGuessr
Author: María Ruiz Ortega
Author-email: ruizormaria@gmail.com
License: GPLv3
Classifier: Development Status :: 3 - Alpha
Classifier: Intended Audience :: Developers
Classifier: Intended Audience :: Healthcare Industry
Classifier: Intended Audience :: Science/Research
Classifier: Topic :: Scientific/Engineering :: Bio-Informatics
Classifier: Topic :: Scientific/Engineering :: Medical Science Apps.
Classifier: License :: OSI Approved :: GNU General Public License v3 (GPLv3)
Classifier: Natural Language :: English
Classifier: Programming Language :: Python :: 3.6
License-File: LICENSE
Requires-Dist: numpy
Requires-Dist: scikit-learn
Requires-Dist: pandas
Requires-Dist: tqdm
